densecurves/__init__.py
densecurves/_plot.py
densecurves/binary.py
densecurves/gray.py
densecurves/hilbert.py
densecurves/lebesgue.py
densecurves/linear.py
densecurves-0.2.1.dist-info/METADATA
densecurves-0.2.1.dist-info/WHEEL
densecurves-0.2.1.dist-info/RECORD
